avtocod/__init__.py
avtocod/avtocod.py
avtocod/consts.py
avtocod/exceptions.py
avtocod/methods/__init__.py
avtocod/methods/authorization.py
avtocod/methods/base.py
avtocod/methods/create_report.py
avtocod/methods/get_balance.py
avtocod/methods/get_report.py
avtocod/methods/get_reports.py
avtocod/methods/get_token.py
avtocod/methods/multirequest.py
avtocod/methods/order_repair.py
avtocod/methods/upgrade_report.py
avtocod/mixins.py
avtocod/pipeline.py
avtocod/session/__init__.py
avtocod/session/aiohttp.py
avtocod/session/base.py
avtocod/session/middlewares/__init__.py
avtocod/session/middlewares/base.py
avtocod/session/middlewares/relogin.py
avtocod/session/middlewares/request_logging.py
avtocod/types/__init__.py
avtocod/types/base.py
avtocod/types/profile/__init__.py
avtocod/types/profile/profile.py
avtocod/types/profile/token.py
avtocod/types/report/__init__.py
avtocod/types/report/generation.py
avtocod/types/report/query_type.py
avtocod/types/report/report.py
avtocod/types/report/report_entities/__init__.py
avtocod/types/report/report_entities/accidents.py
avtocod/types/report/report_entities/additional_info.py
avtocod/types/report/report_entities/calculate.py
avtocod/types/report/report_entities/fines.py
avtocod/types/report/report_entities/gots_action.py
avtocod/types/report/report_entities/identifiers.py
avtocod/types/report/report_entities/last_generation_stat.py
avtocod/types/report/report_entities/market_price.py
avtocod/types/report/report_entities/metadata.py
avtocod/types/report/report_entities/mileages.py
avtocod/types/report/report_entities/owner.py
avtocod/types/report/report_entities/photos.py
avtocod/types/report/report_entities/query.py
avtocod/types/report/report_entities/registration_actions.py
avtocod/types/report/report_entities/restrictions.py
avtocod/types/report/report_entities/state.py
avtocod/types/report/report_entities/stealings.py
avtocod/types/report/report_entities/tech_data.py
avtocod/types/report/report_entities/utilization.py
avtocod-1.0.0.dist-info/LICENSE
avtocod-1.0.0.dist-info/WHEEL
avtocod-1.0.0.dist-info/METADATA
avtocod-1.0.0.dist-info/RECORD
